MANIFEST.in
README.rst
requirements.txt
setup.py
edr_gp.egg-info/PKG-INFO
edr_gp.egg-info/SOURCES.txt
edr_gp.egg-info/dependency_links.txt
edr_gp.egg-info/requires.txt
edr_gp.egg-info/top_level.txt
edrgp/__init__.py
edrgp/base.py
edrgp/datasets.py
edrgp/edr.py
edrgp/utils.py
edrgp/gp_model/__init__.py
edrgp/gp_model/base.py
edrgp/gp_model/classification.py
edrgp/gp_model/regression.py
edrgp/tests/__init__.py
edrgp/tests/test_edr.py