Metadata-Version: 1.1
Name: edr-gp
Version: 0.2.6
Summary: Effective Dimensionality Reduction based on Gaussian Processes
Home-page: https://github.com/neuro-ml/edr-gp
Author: Neuro.ml group
Author-email: belyaevmichel+edr-gp@gmail.com
License: MIT
Platform: UNKNOWN
Classifier: Development Status :: 2 - Pre-Alpha
Classifier: Intended Audience :: Science/Research
Classifier: Topic :: Scientific/Engineering
Classifier: License :: OSI Approved :: MIT License
Classifier: Programming Language :: Python :: 2
Classifier: Programming Language :: Python :: 2.7
Classifier: Programming Language :: Python :: 3
Classifier: Programming Language :: Python :: 3.3
Classifier: Programming Language :: Python :: 3.4
Classifier: Programming Language :: Python :: 3.5
Classifier: Programming Language :: Python :: 3.5
